{"Tools": 0.5137, "Financial": 0.4615, "Messaging": 0.8041, "eCommerce": 0.4302, "Payments": 0.6235, "Social": 0.35, "Enterprise": 0.2911, "Mapping": 0.3881, "Telephony": 0.2105, "Science": 0.2727, "Government": 0.2545, "Email": 0.4375, "Security": 0.1064, "Reference": 0.1915, "Video": 0.5319, "Travel": 0.3778, "Sports": 0.6047, "Search": 0.1395, "Advertising": 0.3095, "Transportation": 0.2857, "Education": 0.488, "Games": 0.4615, "Music": 0.811, "Photos": 0.2857, "Cloud": 0.4545, "Bitcoin": 0.8571, "Project Management": 0.25, "Data": 0.714, "Backend": 0.741, "Database": 0.0, "Shipping": 0.5769, "Weather": 0.6957, "Application Development": 0.0, "Analytics": 0.87, "Internet of Things": 0.909, "Medical": 0.952, "Real Estate": 0.4286, "Events": 0.619, "Banking": 0.40, "Stocks": 0.7368, "Entertainment": 0.0, "Storage": 0.4211, "Marketing": 0.375, "File Sharing": 0.625, "News Services": 0.1875, "Domains": 0.6875, "Chat": 0.3125, "Media": 0.125, "Images": 0.20, "Other": 0.0}